dynapsys/__init__.py
dynapsys/cli.py
dynapsys/config.py
dynapsys/deployment.py
dynapsys/dns.py
dynapsys/git.py
dynapsys/utils.py
dynapsys-0.2.0.dist-info/METADATA
dynapsys-0.2.0.dist-info/WHEEL
dynapsys-0.2.0.dist-info/entry_points.txt
dynapsys-0.2.0.dist-info/top_level.txt
dynapsys-0.2.0.dist-info/RECORD
