Metadata-Version: 2.1
Name: dynapsys
Version: 0.2.0
Summary: Dynamic Python System Deployment Tools
Home-page: https://github.com/dynapsys/dynapsys
Author: Tom
Classifier: Development Status :: 3 - Alpha
Classifier: Intended Audience :: Developers
Classifier: Topic :: Software Development :: Build Tools
Classifier: Topic :: System :: Systems Administration
Classifier: Topic :: Internet :: WWW/HTTP :: HTTP Servers
Classifier: License :: OSI Approved :: Apache Software License
Classifier: Programming Language :: Python :: 3
Classifier: Programming Language :: Python :: 3.6
Classifier: Programming Language :: Python :: 3.7
Classifier: Programming Language :: Python :: 3.8
Classifier: Programming Language :: Python :: 3.9
Classifier: Operating System :: POSIX :: Linux
Requires-Python: >=3.6
Requires-Dist: requests>=2.31.0
Requires-Dist: urllib3>=2.0.0
Requires-Dist: psutil>=5.9.0
Requires-Dist: click>=8.1.0
Requires-Dist: python-dotenv>=1.0.0
Requires-Dist: structlog>=23.1.0
Requires-Dist: typing-extensions>=4.7.0; python_version < "3.8"
Provides-Extra: dev
Requires-Dist: pytest>=7.0.0; extra == "dev"
Requires-Dist: pytest-cov>=4.0.0; extra == "dev"
Requires-Dist: pytest-mock>=3.10.0; extra == "dev"
Requires-Dist: coverage>=7.0.0; extra == "dev"
Requires-Dist: flake8>=6.0.0; extra == "dev"
Requires-Dist: black>=23.0.0; extra == "dev"
Requires-Dist: isort>=5.12.0; extra == "dev"
Requires-Dist: mypy>=1.0.0; extra == "dev"
Requires-Dist: sphinx>=6.0.0; extra == "dev"
Requires-Dist: sphinx-rtd-theme>=1.2.0; extra == "dev"
Requires-Dist: build>=0.10.0; extra == "dev"
Requires-Dist: twine>=4.0.0; extra == "dev"
Requires-Dist: wheel>=0.40.0; extra == "dev"
Requires-Dist: pre-commit>=3.3.0; extra == "dev"
